esp_rainmaker_cli-1.9.1.dist-info/licenses/LICENSE
rainmaker/__init__.py
rainmaker/rainmaker.py
rainmaker/version.py
rmaker_cmd/__init__.py
rmaker_cmd/browserlogin.py
rmaker_cmd/cmd_response.py
rmaker_cmd/group.py
rmaker_cmd/node.py
rmaker_cmd/provision.py
rmaker_cmd/test.py
rmaker_cmd/user.py
rmaker_cmd/html/welcome.html
rmaker_lib/__init__.py
rmaker_lib/cmd_response.py
rmaker_lib/configmanager.py
rmaker_lib/constants.py
rmaker_lib/device.py
rmaker_lib/envval.py
rmaker_lib/exceptions.py
rmaker_lib/logger.py
rmaker_lib/node.py
rmaker_lib/profile_manager.py
rmaker_lib/profile_utils.py
rmaker_lib/schedule_utils.py
rmaker_lib/serverconfig.py
rmaker_lib/service.py
rmaker_lib/session.py
rmaker_lib/simple_local_control.py
rmaker_lib/user.py
rmaker_tools/__init__.py
rmaker_tools/common/__init__.py
rmaker_tools/common/discovery/__init__.py
rmaker_tools/common/discovery/mdns_discovery.py
rmaker_tools/common/prov/__init__.py
rmaker_tools/common/prov/wifi_ctrl.py
rmaker_tools/common/prov/wifi_prov.py
rmaker_tools/common/prov/wifi_scan.py
rmaker_tools/common/security/__init__.py
rmaker_tools/common/security/security.py
rmaker_tools/common/security/security0.py
rmaker_tools/common/security/security1.py
rmaker_tools/common/security/security2.py
rmaker_tools/common/security/srp6a.py
rmaker_tools/common/transport/__init__.py
rmaker_tools/common/transport/ble_cli.py
rmaker_tools/common/transport/transport.py
rmaker_tools/common/transport/transport_ble.py
rmaker_tools/common/transport/transport_console.py
rmaker_tools/common/transport/transport_http.py
rmaker_tools/common/utils/__init__.py
rmaker_tools/common/utils/convenience.py
rmaker_tools/rmaker_claim/__init__.py
rmaker_tools/rmaker_claim/claim.py
rmaker_tools/rmaker_claim/claim_config.py
rmaker_tools/rmaker_local_ctrl/__init__.py
rmaker_tools/rmaker_local_ctrl/constants_pb2.py
rmaker_tools/rmaker_local_ctrl/esp_local_ctrl.py
rmaker_tools/rmaker_local_ctrl/esp_local_ctrl_pb2.py
rmaker_tools/rmaker_local_ctrl/esp_prov.py
rmaker_tools/rmaker_local_ctrl/esp_rainmaker_ctrl.py
esp_rainmaker_cli-1.9.1.dist-info/METADATA
esp_rainmaker_cli-1.9.1.dist-info/WHEEL
esp_rainmaker_cli-1.9.1.dist-info/entry_points.txt
esp_rainmaker_cli-1.9.1.dist-info/top_level.txt
esp_rainmaker_cli-1.9.1.dist-info/RECORD
