Metadata-Version: 2.4
Name: esp-rainmaker-cli
Version: 1.9.1
Summary: A python utility to perform host based claiming
Home-page: https://github.com/espressif/esp-rainmaker-cli
Author: Espressif Systems
Author-email: 
License: Apache-2.0
Project-URL: Documentation, https://rainmaker.espressif.com/docs/cli-setup
Project-URL: Source, https://github.com/espressif/esp-rainmaker-cli
Project-URL: Changelog, https://github.com/espressif/esp-rainmaker-cli/blob/master/CHANGELOG.md
Classifier: License :: OSI Approved :: Apache Software License
Classifier: Intended Audience :: Developers
Classifier: Natural Language :: English
Classifier: Operating System :: POSIX
Classifier: Operating System :: MacOS :: MacOS X
Classifier: Topic :: Software Development :: Embedded Systems
Classifier: Programming Language :: Python :: 3.9
Classifier: Programming Language :: Python :: 3.10
Classifier: Programming Language :: Python :: 3.11
Requires-Python: >=3.9
License-File: LICENSE
Requires-Dist: requests>=2.22.0
Requires-Dist: cmd2>=0.9.18
Requires-Dist: protobuf>=5.29.3
Requires-Dist: packaging>=19.2
Requires-Dist: oauth2client>=4.1.3
Requires-Dist: click>=5.0
Requires-Dist: pyserial>=3.0
Requires-Dist: future>=0.15.2
Requires-Dist: pyparsing>=2.4.0
Requires-Dist: pyelftools>=0.22
Requires-Dist: esptool>=4.4
Requires-Dist: esp-secure-cert-tool==1.0.1
Requires-Dist: setuptools
Requires-Dist: esp_idf_nvs_partition_gen>=0.1.6
Requires-Dist: bleak>=0.20.0
Requires-Dist: zeroconf>=0.131.0
Dynamic: author
Dynamic: classifier
Dynamic: description
Dynamic: description-content-type
Dynamic: home-page
Dynamic: license
Dynamic: license-file
Dynamic: project-url
Dynamic: requires-dist
Dynamic: requires-python
Dynamic: summary
